Workbook

Sheet Base
A2: 45870 | J2: Saldo atual | K2: Gasto atual
A3: DESPESAS DO MÊS | H3: RECEITA | I3: 2034.29 | J3: =SUM(I3-K3) -> 708.09 | K3: =SUM(D5:D63) -> 1326.2
B4: DATA | C4: DESPESA | D4: VALOR | E4: CATEGORIA | F4: TIPO
A5: FIXO | B5: 45874 | C5: Claro | D5: 45.5 | E5: Internet | F5: Despesa fixa | I5: META | J5: ATUAL | K5: REST/MÊS
B6: 45874 | C6: Internet | D6: 119.9 | E6: Internet | F6: Despesa fixa | H6: Investimento | I6: - | J6: - | K6: -
B7: 45874 | C7: Spotify | D7: 27.9 | E7: Streaming | F7: Despesa fixa | H7: Despesa fixa | I7: =SUMIF(F5:F62,"Despesa fixa",D5:D62) -> 1326.2 | J7: =SUMIF(F5:F62,"Despesa fixa",D5:D62) -> 1326.2 | K7: =SUM(I7-J7) -> 0
B8: 45874 | C8: Disney Plus | D8: 62.9 | E8: Streaming | F8: Despesa fixa | H8: Despesa variavel | I8: =SUM(I3-I7) -> 708.09 | J8: =SUMIF(F5:F62,"Despesa variavel",D5:D62) -> 0 | K8: =SUM(I8-J8) -> 708.09
B9: 45874 | C9: Aluguel | D9: 850 | E9: Moradia | F9: Despesa fixa | H9: TOTAL | J9: =SUM(J6:J8) -> 1326.2 | K9: =SUM(K6:K8) -> 708.09
B10: 45874 | C10: Luz | D10: 220 | E10: Contas | F10: Despesa fixa
H11: Semanas no mês | I11: 4
H12: Gasto variavel sem. | I12: =SUM(I8/I11) -> 177.0225
I14: META | J14: ATUAL | K14: REST/SEM
A15: SEMANA 1 | H15: SEMANA 1 (01 a 04) | I15: =SUM(I12) -> 177.0225 | J15: =SUMIF(F13:F22,"Despesa variavel",D13:D22) -> 0 | K15: =SUM(I15-J15) -> 177.0225
H16: SEMANA 2 (05 a 11) | I16: =SUM(I12) -> 177.0225 | J16: =SUMIF(F23:F32,"Despesa variavel",D23:D32) -> 0 | K16: =SUM(I16-J16) -> 177.0225
H17: SEMANA 3 (12 a 18) | I17: =SUM(I12) -> 177.0225 | J17: =SUMIF(F33:F42,"Despesa variavel",D33:D42) -> 0 | K17: =SUM(I17-J17) -> 177.0225
H18: SEMANA 4 (19 a 25) | I18: =SUM(I12) -> 177.0225 | J18: =SUMIF(F43:F52,"Despesa variavel",D43:D52) -> 0 | K18: =SUM(I18-J18) -> 177.0225
H19: SEMANA 5 (26 a 31) | I19: =SUM(I12) -> 177.0225 | J19: =SUMIF(F53:F62,"Despesa variavel",D53:D62) -> 0 | K19: =SUM(I19-J19) -> 177.0225
H24: Legenda
A25: SEMANA 2 | H25: Transf. p/ Santander | I25: =SUM(D5:D6) -> 165.4
H26: Transf. p/ Inter | I26: =SUM(D7:D8) -> 90.8
H27: Transf. p/ casa | I27: =SUM(D9:D10) -> 1070
H28: Pago | I28: =SUM(I25:I27) -> 1326.2
A35: SEMANA 3
A45: SEMANA 4
A55: SEMANA 5

Sheet Planilha apoio
A1: CATEGORIA | B1: FORMA
A2: Alimentação | B2: Boleto
A3: Aluguel | B3: Crédito
A4: Bebidas | B4: Conta
A5: Estética | B5: Débito
A6: Cabeleireiro | B6: Dinheiro
A7: Calçados | B7: Pix
A8: Combustível | B8: VA/VR
A9: Contas
A10: Crédito Ca
A11: Delivery
A12: Educação
A13: Emergenciais
A14: Entretenimento
A15: Estacionamento
A16: Estudos
A17: Fatura
A18: Gasolina
A19: Imprevistos
A20: Hobbies
... A42: Viagens

Sheet jan-26
B2: 46023
B3: DESPESAS VARIAVEIS | N3: Receitas | O3: Salario | P3: Extra | Q3: Total
B4: CAMILA | H4: LUCAS | N4: Lucas | O4: 3000 | Q4: =SUM(O4+P4) -> 3000
B5: DATA | C5: DESPESA | D5: VALOR | E5: CATEGORIA | F5: FORMA | H5: DATA | I5: DESPESA | J5: VALOR | K5: CATEGORIA | L5: FORMA | N5: Camila | O5: 2000 | Q5: =SUM(O5+P5) -> 2000
N6: VR | O6: 1012 | P6: Total | Q6: =SUM(Q4:Q5) -> 5000
P7: Total + VR | Q7: =SUM(Q6+O6) -> 6012
N9: Invest. | O9: 1000
N10: Desp. Fixa | O10: =SUM(P16:P19) + SUM(P21:P33) -> 3669.08
N11: Desp. Var | O11: {=SUM(D6:D35+J6:J35)} -> 0
N12: TOTAL | O12: =SUM(O9:O11) -> 4669.08
N14: DESPESAS FIXA
N15: DATA | O15: DESPESA | P15: VALOR | Q15: CATEGORIA | R15: FORMA
N16: 45662 | O16: Aluguel | P16: 850 | Q16: Aluguel | R16: Pix
N17: 45662 | O17: Luz | P17: 220 | Q17: Luz | R17: Pix
N18: 45662 | O18: Cartão | P18: 1900 | Q18: Fatura | R18: Pix
N19: 45662 | O19: Faculdade | P19: 143.15 | Q19: Estudos | R19: Boleto
N20: DESPESAS FIXA CARTÃO
N21: 45693 | O21: Spotify | P21: 40.9 | Q21: Streaming | R21: Crédito
N22: 45693 | O22: Disney | P22: 66.9 | Q22: Streaming | R22: Crédito
N23: 45693 | O23: Gamepass | P23: 59.99 | Q23: Streaming | R23: Crédito
N24: 45693 | O24: Claro Casa | P24: 119.9 | Q24: Internet | R24: Crédito
N25: 45693 | O25: Claro Lucas | P25: 50.08 | Q25: Internet | R25: Crédito
N26: 45693 | O26: Claro Amor | P26: 38.36 | Q26: Internet | R26: Crédito
N27: 45693 | O27: Semova Amor (4/12) | P27: 89.9 | Q27: Saúde | R27: Crédito
N28: 45693 | O28: Wellhub Lucas | P28: 89.9 | Q28: Saúde | R28: Crédito
O35: Fatura prox. Mês | P35: =SUMIF(F6:F35, "Crédito", D6:D35) + SUMIF(L6:L35, "Crédito", J6:J35) + SUMIF(R16:R33, "Crédito", P16:P33) -> 555.93

Sheet fev-26
B2: 46054
B3: DESPESAS VARIAVEIS | N3: Receitas | O3: Salario | P3: Extra | Q3: Total
B4: CAMILA | H4: LUCAS | N4: Lucas | O4: 3000 | Q4: =SUM(O4+P4) -> 3000
B5: DATA | C5: DESPESA | D5: VALOR | E5: CATEGORIA | F5: FORMA | H5: DATA | I5: DESPESA | J5: VALOR | K5: CATEGORIA | L5: FORMA | N5: Camila | O5: 2000 | Q5: =SUM(O5+P5) -> 2000
N6: VR | O6: 1012 | P6: Total | Q6: =SUM(Q4:Q5) -> 5000
P7: Total + VR | Q7: =SUM(Q6+O6) -> 6012
N9: Invest. | O9: 1000
N10: Desp. Fixa | O10: =SUM(P16:P19) + SUM(P21:P33) -> 2325.01
N11: Desp. Var | O11: {=SUM(D6:D35+J6:J35)} -> 0
N12: TOTAL | O12: =SUM(O9:O11) -> 3325.01
N14: DESPESAS FIXA
N15: DATA | O15: DESPESA | P15: VALOR | Q15: CATEGORIA | R15: FORMA
N16: 45693 | O16: Aluguel | P16: 850 | Q16: Aluguel | R16: Pix
N17: 45693 | O17: Luz | P17: 220 | Q17: Luz | R17: Pix
N18: 45693 | O18: Cartão | P18: =SUM('jan-26'!P35) -> 555.93 | Q18: Fatura | R18: Pix
N19: 45693 | O19: Faculdade | P19: 143.15 | Q19: Estudos | R19: Boleto
N20: DESPESAS FIXA CARTÃO
N21: 45721 | O21: Spotify | P21: 40.9 | Q21: Streaming | R21: Crédito
N22: 45721 | O22: Disney | P22: 66.9 | Q22: Streaming | R22: Crédito
N23: 45721 | O23: Gamepass | P23: 59.99 | Q23: Streaming | R23: Crédito
N24: 45721 | O24: Claro Casa | P24: 119.9 | Q24: Internet | R24: Crédito
N25: 45721 | O25: Claro Lucas | P25: 50.08 | Q25: Internet | R25: Crédito
N26: 45721 | O26: Claro Amor | P26: 38.36 | Q26: Internet | R26: Crédito
N27: 45721 | O27: Semova Amor (5/12) | P27: 89.9 | Q27: Saúde | R27: Crédito
N28: 45721 | O28: Wellhub Lucas | P28: 89.9 | Q28: Saúde | R28: Crédito
O35: Fatura prox. Mês | P35: =SUMIF(F6:F35, "Crédito", D6:D35) + SUMIF(L6:L35, "Crédito", J6:J35) + SUMIF(R16:R33, "Crédito", P16:P33) -> 555.93

Sheet mar-26
B2: 46082
B3: DESPESAS VARIAVEIS | N3: Receitas | O3: Salario | P3: Extra | Q3: Total
B4: CAMILA | H4: LUCAS | N4: Lucas | O4: 3000 | Q4: =SUM(O4+P4) -> 3000
B5: DATA | C5: DESPESA | D5: VALOR | E5: CATEGORIA | F5: FORMA | H5: DATA | I5: DESPESA | J5: VALOR | K5: CATEGORIA | L5: FORMA | N5: Camila | O5: 2000 | Q5: =SUM(O5+P5) -> 2000
N6: VR | O6: 1012 | P6: Total | Q6: =SUM(Q4:Q5) -> 5000
P7: Total + VR | Q7: =SUM(Q6+O6) -> 6012
N9: Invest. | O9: 1000
N10: Desp. Fixa | O10: =SUM(P16:P19) + SUM(P21:P33) -> 2325.01
N11: Desp. Var | O11: {=SUM(D6:D35+J6:J35)} -> 0
N12: TOTAL | O12: =SUM(O9:O11) -> 3325.01
N14: DESPESAS FIXA
N15: DATA | O15: DESPESA | P15: VALOR | Q15: CATEGORIA | R15: FORMA
N16: 45721 | O16: Aluguel | P16: 850 | Q16: Aluguel | R16: Pix
N17: 45721 | O17: Luz | P17: 220 | Q17: Luz | R17: Pix
N18: 45721 | O18: Cartão | P18: =SUM('jan-26'!P35) -> 555.93 | Q18: Fatura | R18: Pix
N19: 45721 | O19: Faculdade | P19: 143.15 | Q19: Estudos | R19: Boleto
N20: DESPESAS FIXA CARTÃO
N21: 45752 | O21: Spotify | P21: 40.9 | Q21: Streaming | R21: Crédito
N22: 45752 | O22: Disney | P22: 66.9 | Q22: Streaming | R22: Crédito
N23: 45752 | O23: Gamepass | P23: 59.99 | Q23: Streaming | R23: Crédito
N24: 45752 | O24: Claro Casa | P24: 119.9 | Q24: Internet | R24: Crédito
N25: 45752 | O25: Claro Lucas | P25: 50.08 | Q25: Internet | R25: Crédito
N26: 45752 | O26: Claro Amor | P26: 38.36 | Q26: Internet | R26: Crédito
N27: 45752 | O27: Semova Amor (6/12) | P27: 89.9 | Q27: Saúde | R27: Crédito
N28: 45752 | O28: Wellhub Lucas | P28: 89.9 | Q28: Saúde | R28: Crédito
O35: Fatura prox. Mês | P35: =SUMIF(F6:F35, "Crédito", D6:D35) + SUMIF(L6:L35, "Crédito", J6:J35) + SUMIF(R16:R33, "Crédito", P16:P33) -> 555.93

Sheet abr-26
B2: 46113
B3: DESPESAS VARIAVEIS | N3: Receitas | O3: Salario | P3: Extra | Q3: Total
B4: CAMILA | H4: LUCAS | N4: Lucas | O4: 3000 | Q4: =SUM(O4+P4) -> 3000
B5: DATA | C5: DESPESA | D5: VALOR | E5: CATEGORIA | F5: FORMA | H5: DATA | I5: DESPESA | J5: VALOR | K5: CATEGORIA | L5: FORMA | N5: Camila | O5: 2000 | Q5: =SUM(O5+P5) -> 2000
N6: VR | O6: 1012 | P6: Total | Q6: =SUM(Q4:Q5) -> 5000
P7: Total + VR | Q7: =SUM(Q6+O6) -> 6012
N9: Invest. | O9: 1000
N10: Desp. Fixa | O10: =SUM(P16:P19) + SUM(P21:P33) -> 2325.01
N11: Desp. Var | O11: {=SUM(D6:D35+J6:J35)} -> 0
N12: TOTAL | O12: =SUM(O9:O11) -> 3325.01
N14: DESPESAS FIXA
N15: DATA | O15: DESPESA | P15: VALOR | Q15: CATEGORIA | R15: FORMA
N16: 45752 | O16: Aluguel | P16: 850 | Q16: Aluguel | R16: Pix
N17: 45752 | O17: Luz | P17: 220 | Q17: Luz | R17: Pix
N18: 45752 | O18: Cartão | P18: =SUM('jan-26'!P35) -> 555.93 | Q18: Fatura | R18: Pix
N19: 45752 | O19: Faculdade | P19: 143.15 | Q19: Estudos | R19: Boleto
N20: DESPESAS FIXA CARTÃO
N21: 45782 | O21: Spotify | P21: 40.9 | Q21: Streaming | R21: Crédito
N22: 45782 | O22: Disney | P22: 66.9 | Q22: Streaming | R22: Crédito
N23: 45782 | O23: Gamepass | P23: 59.99 | Q23: Streaming | R23: Crédito
N24: 45782 | O24: Claro Casa | P24: 119.9 | Q24: Internet | R24: Crédito
N25: 45782 | O25: Claro Lucas | P25: 50.08 | Q25: Internet | R25: Crédito
N26: 45782 | O26: Claro Amor | P26: 38.36 | Q26: Internet | R26: Crédito
N27: 45782 | O27: Semova Amor (7/12) | P27: 89.9 | Q27: Saúde | R27: Crédito
N28: 45782 | O28: Wellhub Lucas | P28: 89.9 | Q28: Saúde | R28: Crédito
O35: Fatura prox. Mês | P35: =SUMIF(F6:F35, "Crédito", D6:D35) + SUMIF(L6:L35, "Crédito", J6:J35) + SUMIF(R16:R33, "Crédito", P16:P33) -> 555.93

Sheet mai-26
B2: 46143
B3: DESPESAS VARIAVEIS | N3: Receitas | O3: Salario | P3: Extra | Q3: Total
B4: CAMILA | H4: LUCAS | N4: Lucas | O4: 3000 | Q4: =SUM(O4+P4) -> 3000
B5: DATA | C5: DESPESA | D5: VALOR | E5: CATEGORIA | F5: FORMA | H5: DATA | I5: DESPESA | J5: VALOR | K5: CATEGORIA | L5: FORMA | N5: Camila | O5: 2000 | Q5: =SUM(O5+P5) -> 2000
N6: VR | O6: 1012 | P6: Total | Q6: =SUM(Q4:Q5) -> 5000
P7: Total + VR | Q7: =SUM(Q6+O6) -> 6012
N9: Invest. | O9: 1000
N10: Desp. Fixa | O10: =SUM(P16:P19) + SUM(P21:P33) -> 2325.01
N11: Desp. Var | O11: {=SUM(D6:D35+J6:J35)} -> 0
N12: TOTAL | O12: =SUM(O9:O11) -> 3325.01
N14: DESPESAS FIXA
N15: DATA | O15: DESPESA | P15: VALOR | Q15: CATEGORIA | R15: FORMA
N16: 45782 | O16: Aluguel | P16: 850 | Q16: Aluguel | R16: Pix
N17: 45782 | O17: Luz | P17: 220 | Q17: Luz | R17: Pix
N18: 45782 | O18: Cartão | P18: =SUM('jan-26'!P35) -> 555.93 | Q18: Fatura | R18: Pix
N19: 45782 | O19: Faculdade | P19: 143.15 | Q19: Estudos | R19: Boleto
N20: DESPESAS FIXA CARTÃO
N21: 45813 | O21: Spotify | P21: 40.9 | Q21: Streaming | R21: Crédito
N22: 45813 | O22: Disney | P22: 66.9 | Q22: Streaming | R22: Crédito
N23: 45813 | O23: Gamepass | P23: 59.99 | Q23: Streaming | R23: Crédito
N24: 45813 | O24: Claro Casa | P24: 119.9 | Q24: Internet | R24: Crédito
N25: 45813 | O25: Claro Lucas | P25: 50.08 | Q25: Internet | R25: Crédito
N26: 45813 | O26: Claro Amor | P26: 38.36 | Q26: Internet | R26: Crédito
N27: 45813 | O27: Semova Amor (8/12) | P27: 89.9 | Q27: Saúde | R27: Crédito
N28: 45813 | O28: Wellhub Lucas | P28: 89.9 | Q28: Saúde | R28: Crédito
O35: Fatura prox. Mês | P35: =SUMIF(F6:F35, "Crédito", D6:D35) + SUMIF(L6:L35, "Crédito", J6:J35) + SUMIF(R16:R33, "Crédito", P16:P33) -> 555.93

Sheet jun-26
B2: 46174
B3: DESPESAS VARIAVEIS | N3: Receitas | O3: Salario | P3: Extra | Q3: Total
B4: CAMILA | H4: LUCAS | N4: Lucas | O4: 3000 | Q4: =SUM(O4+P4) -> 3000
B5: DATA | C5: DESPESA | D5: VALOR | E5: CATEGORIA | F5: FORMA | H5: DATA | I5: DESPESA | J5: VALOR | K5: CATEGORIA | L5: FORMA | N5: Camila | O5: 2000 | Q5: =SUM(O5+P5) -> 2000
N6: VR | O6: 1012 | P6: Total | Q6: =SUM(Q4:Q5) -> 5000
P7: Total + VR | Q7: =SUM(Q6+O6) -> 6012
N9: Invest. | O9: 1000
N10: Desp. Fixa | O10: =SUM(P16:P19) + SUM(P21:P33) -> 2325.01
N11: Desp. Var | O11: {=SUM(D6:D35+J6:J35)} -> 0
N12: TOTAL | O12: =SUM(O9:O11) -> 3325.01
N14: DESPESAS FIXA
N15: DATA | O15: DESPESA | P15: VALOR | Q15: CATEGORIA | R15: FORMA
N16: 45813 | O16: Aluguel | P16: 850 | Q16: Aluguel | R16: Pix
N17: 45813 | O17: Luz | P17: 220 | Q17: Luz | R17: Pix
N18: 45813 | O18: Cartão | P18: =SUM('jan-26'!P35) -> 555.93 | Q18: Fatura | R18: Pix
N19: 45813 | O19: Faculdade | P19: 143.15 | Q19: Estudos | R19: Boleto
N20: DESPESAS FIXA CARTÃO
N21: 45843 | O21: Spotify | P21: 40.9 | Q21: Streaming | R21: Crédito
N22: 45843 | O22: Disney | P22: 66.9 | Q22: Streaming | R22: Crédito
N23: 45843 | O23: Gamepass | P23: 59.99 | Q23: Streaming | R23: Crédito
N24: 45843 | O24: Claro Casa | P24: 119.9 | Q24: Internet | R24: Crédito
N25: 45843 | O25: Claro Lucas | P25: 50.08 | Q25: Internet | R25: Crédito
N26: 45843 | O26: Claro Amor | P26: 38.36 | Q26: Internet | R26: Crédito
N27: 45843 | O27: Semova Amor (9/12) | P27: 89.9 | Q27: Saúde | R27: Crédito
N28: 45843 | O28: Wellhub Lucas | P28: 89.9 | Q28: Saúde | R28: Crédito
O35: Fatura prox. Mês | P35: =SUMIF(F6:F35, "Crédito", D6:D35) + SUMIF(L6:L35, "Crédito", J6:J35) + SUMIF(R16:R33, "Crédito", P16:P33) -> 555.93

Sheet jul-26
B2: 46204
B3: DESPESAS VARIAVEIS | N3: Receitas | O3: Salario | P3: Extra | Q3: Total
B4: CAMILA | H4: LUCAS | N4: Lucas | O4: 3000 | Q4: =SUM(O4+P4) -> 3000
B5: DATA | C5: DESPESA | D5: VALOR | E5: CATEGORIA | F5: FORMA | H5: DATA | I5: DESPESA | J5: VALOR | K5: CATEGORIA | L5: FORMA | N5: Camila | O5: 2000 | Q5: =SUM(O5+P5) -> 2000
N6: VR | O6: 1012 | P6: Total | Q6: =SUM(Q4:Q5) -> 5000
P7: Total + VR | Q7: =SUM(Q6+O6) -> 6012
N9: Invest. | O9: 1000
N10: Desp. Fixa | O10: =SUM(P16:P19) + SUM(P21:P33) -> 2325.01
N11: Desp. Var | O11: {=SUM(D6:D35+J6:J35)} -> 0
N12: TOTAL | O12: =SUM(O9:O11) -> 3325.01
N14: DESPESAS FIXA
N15: DATA | O15: DESPESA | P15: VALOR | Q15: CATEGORIA | R15: FORMA
N16: 45843 | O16: Aluguel | P16: 850 | Q16: Aluguel | R16: Pix
N17: 45843 | O17: Luz | P17: 220 | Q17: Luz | R17: Pix
N18: 45843 | O18: Cartão | P18: =SUM('jan-26'!P35) -> 555.93 | Q18: Fatura | R18: Pix
N19: 45843 | O19: Faculdade | P19: 143.15 | Q19: Estudos | R19: Boleto
N20: DESPESAS FIXA CARTÃO
N21: 45874 | O21: Spotify | P21: 40.9 | Q21: Streaming | R21: Crédito
N22: 45874 | O22: Disney | P22: 66.9 | Q22: Streaming | R22: Crédito
N23: 45874 | O23: Gamepass | P23: 59.99 | Q23: Streaming | R23: Crédito
N24: 45874 | O24: Claro Casa | P24: 119.9 | Q24: Internet | R24: Crédito
N25: 45874 | O25: Claro Lucas | P25: 50.08 | Q25: Internet | R25: Crédito
N26: 45874 | O26: Claro Amor | P26: 38.36 | Q26: Internet | R26: Crédito
N27: 45874 | O27: Semova Amor (10/12) | P27: 89.9 | Q27: Saúde | R27: Crédito
N28: 45874 | O28: Wellhub Lucas | P28: 89.9 | Q28: Saúde | R28: Crédito
O35: Fatura prox. Mês | P35: =SUMIF(F6:F35, "Crédito", D6:D35) + SUMIF(L6:L35, "Crédito", J6:J35) + SUMIF(R16:R33, "Crédito", P16:P33) -> 555.93

Sheet ago-26
B2: 46235
B3: DESPESAS VARIAVEIS | N3: Receitas | O3: Salario | P3: Extra | Q3: Total
B4: CAMILA | H4: LUCAS | N4: Lucas | O4: 3000 | Q4: =SUM(O4+P4) -> 3000
B5: DATA | C5: DESPESA | D5: VALOR | E5: CATEGORIA | F5: FORMA | H5: DATA | I5: DESPESA | J5: VALOR | K5: CATEGORIA | L5: FORMA | N5: Camila | O5: 2000 | Q5: =SUM(O5+P5) -> 2000
N6: VR | O6: 1012 | P6: Total | Q6: =SUM(Q4:Q5) -> 5000
P7: Total + VR | Q7: =SUM(Q6+O6) -> 6012
N9: Invest. | O9: 1000
N10: Desp. Fixa | O10: =SUM(P16:P19) + SUM(P21:P33) -> 2325.01
N11: Desp. Var | O11: {=SUM(D6:D35+J6:J35)} -> 0
N12: TOTAL | O12: =SUM(O9:O11) -> 3325.01
N14: DESPESAS FIXA
N15: DATA | O15: DESPESA | P15: VALOR | Q15: CATEGORIA | R15: FORMA
N16: 45874 | O16: Aluguel | P16: 850 | Q16: Aluguel | R16: Pix
N17: 45874 | O17: Luz | P17: 220 | Q17: Luz | R17: Pix
N18: 45874 | O18: Cartão | P18: =SUM('jan-26'!P35) -> 555.93 | Q18: Fatura | R18: Pix
N19: 45874 | O19: Faculdade | P19: 143.15 | Q19: Estudos | R19: Boleto
N20: DESPESAS FIXA CARTÃO
N21: 45905 | O21: Spotify | P21: 40.9 | Q21: Streaming | R21: Crédito
N22: 45905 | O22: Disney | P22: 66.9 | Q22: Streaming | R22: Crédito
N23: 45905 | O23: Gamepass | P23: 59.99 | Q23: Streaming | R23: Crédito
N24: 45905 | O24: Claro Casa | P24: 119.9 | Q24: Internet | R24: Crédito
N25: 45905 | O25: Claro Lucas | P25: 50.08 | Q25: Internet | R25: Crédito
N26: 45905 | O26: Claro Amor | P26: 38.36 | Q26: Internet | R26: Crédito
N27: 45905 | O27: Semova Amor (11/12) | P27: 89.9 | Q27: Saúde | R27: Crédito
N28: 45905 | O28: Wellhub Lucas | P28: 89.9 | Q28: Saúde | R28: Crédito
O35: Fatura prox. Mês | P35: =SUMIF(F6:F35, "Crédito", D6:D35) + SUMIF(L6:L35, "Crédito", J6:J35) + SUMIF(R16:R33, "Crédito", P16:P33) -> 555.93

Sheet set-26
B2: 46266
B3: DESPESAS VARIAVEIS | N3: Receitas | O3: Salario | P3: Extra | Q3: Total
B4: CAMILA | H4: LUCAS | N4: Lucas | O4: 3000 | Q4: =SUM(O4+P4) -> 3000
B5: DATA | C5: DESPESA | D5: VALOR | E5: CATEGORIA | F5: FORMA | H5: DATA | I5: DESPESA | J5: VALOR | K5: CATEGORIA | L5: FORMA | N5: Camila | O5: 2000 | Q5: =SUM(O5+P5) -> 2000
N6: VR | O6: 1012 | P6: Total | Q6: =SUM(Q4:Q5) -> 5000
P7: Total + VR | Q7: =SUM(Q6+O6) -> 6012
N9: Invest. | O9: 1000
N10: Desp. Fixa | O10: =SUM(P16:P19) + SUM(P21:P33) -> 2325.01
N11: Desp. Var | O11: {=SUM(D6:D35+J6:J35)} -> 0
N12: TOTAL | O12: =SUM(O9:O11) -> 3325.01
N14: DESPESAS FIXA
N15: DATA | O15: DESPESA | P15: VALOR | Q15: CATEGORIA | R15: FORMA
N16: 45905 | O16: Aluguel | P16: 850 | Q16: Aluguel | R16: Pix
N17: 45905 | O17: Luz | P17: 220 | Q17: Luz | R17: Pix
N18: 45905 | O18: Cartão | P18: =SUM('jan-26'!P35) -> 555.93 | Q18: Fatura | R18: Pix
N19: 45905 | O19: Faculdade | P19: 143.15 | Q19: Estudos | R19: Boleto
N20: DESPESAS FIXA CARTÃO
N21: 45935 | O21: Spotify | P21: 40.9 | Q21: Streaming | R21: Crédito
N22: 45935 | O22: Disney | P22: 66.9 | Q22: Streaming | R22: Crédito
N23: 45935 | O23: Gamepass | P23: 59.99 | Q23: Streaming | R23: Crédito
N24: 45935 | O24: Claro Casa | P24: 119.9 | Q24: Internet | R24: Crédito
N25: 45935 | O25: Claro Lucas | P25: 50.08 | Q25: Internet | R25: Crédito
N26: 45935 | O26: Claro Amor | P26: 38.36 | Q26: Internet | R26: Crédito
N27: 45935 | O27: Semova Amor (12/12) | P27: 89.9 | Q27: Saúde | R27: Crédito
N28: 45935 | O28: Wellhub Lucas | P28: 89.9 | Q28: Saúde | R28: Crédito
O35: Fatura prox. Mês | P35: =SUMIF(F6:F35, "Crédito", D6:D35) + SUMIF(L6:L35, "Crédito", J6:J35) + SUMIF(R16:R33, "Crédito", P16:P33) -> 555.93

Sheet out-26
B2: 46296
B3: DESPESAS VARIAVEIS | N3: Receitas | O3: Salario | P3: Extra | Q3: Total
B4: CAMILA | H4: LUCAS | N4: Lucas | O4: 3000 | Q4: =SUM(O4+P4) -> 3000
B5: DATA | C5: DESPESA | D5: VALOR | E5: CATEGORIA | F5: FORMA | H5: DATA | I5: DESPESA | J5: VALOR | K5: CATEGORIA | L5: FORMA | N5: Camila | O5: 2000 | Q5: =SUM(O5+P5) -> 2000
N6: VR | O6: 1012 | P6: Total | Q6: =SUM(Q4:Q5) -> 5000
P7: Total + VR | Q7: =SUM(Q6+O6) -> 6012
N9: Invest. | O9: 1000
N10: Desp. Fixa | O10: =SUM(P16:P19) + SUM(P21:P33) -> 2325.01
N11: Desp. Var | O11: {=SUM(D6:D35+J6:J35)} -> 0
N12: TOTAL | O12: =SUM(O9:O11) -> 3325.01
N14: DESPESAS FIXA
N15: DATA | O15: DESPESA | P15: VALOR | Q15: CATEGORIA | R15: FORMA
N16: 45935 | O16: Aluguel | P16: 850 | Q16: Aluguel | R16: Pix
N17: 45935 | O17: Luz | P17: 220 | Q17: Luz | R17: Pix
N18: 45935 | O18: Cartão | P18: =SUM('jan-26'!P35) -> 555.93 | Q18: Fatura | R18: Pix
N19: 45935 | O19: Faculdade | P19: 143.15 | Q19: Estudos | R19: Boleto
N20: DESPESAS FIXA CARTÃO
N21: 45966 | O21: Spotify | P21: 40.9 | Q21: Streaming | R21: Crédito
N22: 45966 | O22: Disney | P22: 66.9 | Q22: Streaming | R22: Crédito
N23: 45966 | O23: Gamepass | P23: 59.99 | Q23: Streaming | R23: Crédito
N24: 45966 | O24: Claro Casa | P24: 119.9 | Q24: Internet | R24: Crédito
N25: 45966 | O25: Claro Lucas | P25: 50.08 | Q25: Internet | R25: Crédito
N26: 45966 | O26: Claro Amor | P26: 38.36 | Q26: Internet | R26: Crédito
N27: 45966 | O27: Semova Amor (1/12) | P27: 89.9 | Q27: Saúde | R27: Crédito
N28: 45966 | O28: Wellhub Lucas | P28: 89.9 | Q28: Saúde | R28: Crédito
O35: Fatura prox. Mês | P35: =SUMIF(F6:F35, "Crédito", D6:D35) + SUMIF(L6:L35, "Crédito", J6:J35) + SUMIF(R16:R33, "Crédito", P16:P33) -> 555.93

Sheet nov-26
B2: 46327
B3: DESPESAS VARIAVEIS | N3: Receitas | O3: Salario | P3: Extra | Q3: Total
B4: CAMILA | H4: LUCAS | N4: Lucas | O4: 3000 | Q4: =SUM(O4+P4) -> 3000
B5: DATA | C5: DESPESA | D5: VALOR | E5: CATEGORIA | F5: FORMA | H5: DATA | I5: DESPESA | J5: VALOR | K5: CATEGORIA | L5: FORMA | N5: Camila | O5: 2000 | Q5: =SUM(O5+P5) -> 2000
N6: VR | O6: 1012 | P6: Total | Q6: =SUM(Q4:Q5) -> 5000
P7: Total + VR | Q7: =SUM(Q6+O6) -> 6012
N9: Invest. | O9: 1000
N10: Desp. Fixa | O10: =SUM(P16:P19) + SUM(P21:P33) -> 2325.01
N11: Desp. Var | O11: {=SUM(D6:D35+J6:J35)} -> 0
N12: TOTAL | O12: =SUM(O9:O11) -> 3325.01
N14: DESPESAS FIXA
N15: DATA | O15: DESPESA | P15: VALOR | Q15: CATEGORIA | R15: FORMA
N16: 45966 | O16: Aluguel | P16: 850 | Q16: Aluguel | R16: Pix
N17: 45966 | O17: Luz | P17: 220 | Q17: Luz | R17: Pix
N18: 45966 | O18: Cartão | P18: =SUM('jan-26'!P35) -> 555.93 | Q18: Fatura | R18: Pix
N19: 45966 | O19: Faculdade | P19: 143.15 | Q19: Estudos | R19: Boleto
N20: DESPESAS FIXA CARTÃO
N21: 45996 | O21: Spotify | P21: 40.9 | Q21: Streaming | R21: Crédito
N22: 45996 | O22: Disney | P22: 66.9 | Q22: Streaming | R22: Crédito
N23: 45996 | O23: Gamepass | P23: 59.99 | Q23: Streaming | R23: Crédito
N24: 45996 | O24: Claro Casa | P24: 119.9 | Q24: Internet | R24: Crédito
N25: 45996 | O25: Claro Lucas | P25: 50.08 | Q25: Internet | R25: Crédito
N26: 45996 | O26: Claro Amor | P26: 38.36 | Q26: Internet | R26: Crédito
N27: 45996 | O27: Semova Amor (2/12) | P27: 89.9 | Q27: Saúde | R27: Crédito
N28: 45996 | O28: Wellhub Lucas | P28: 89.9 | Q28: Saúde | R28: Crédito
O35: Fatura prox. Mês | P35: =SUMIF(F6:F35, "Crédito", D6:D35) + SUMIF(L6:L35, "Crédito", J6:J35) + SUMIF(R16:R33, "Crédito", P16:P33) -> 555.93

Sheet dez-26
B2: 46357
B3: DESPESAS VARIAVEIS | N3: Receitas | O3: Salario | P3: Extra | Q3: Total
B4: CAMILA | H4: LUCAS | N4: Lucas | O4: 3000 | Q4: =SUM(O4+P4) -> 3000
B5: DATA | C5: DESPESA | D5: VALOR | E5: CATEGORIA | F5: FORMA | H5: DATA | I5: DESPESA | J5: VALOR | K5: CATEGORIA | L5: FORMA | N5: Camila | O5: 2000 | Q5: =SUM(O5+P5) -> 2000
N6: VR | O6: 1012 | P6: Total | Q6: =SUM(Q4:Q5) -> 5000
P7: Total + VR | Q7: =SUM(Q6+O6) -> 6012
N9: Invest. | O9: 1000
N10: Desp. Fixa | O10: =SUM(P16:P19) + SUM(P21:P33) -> 2325.01
N11: Desp. Var | O11: {=SUM(D6:D35+J6:J35)} -> 0
N12: TOTAL | O12: =SUM(O9:O11) -> 3325.01
N14: DESPESAS FIXA
N15: DATA | O15: DESPESA | P15: VALOR | Q15: CATEGORIA | R15: FORMA
N16: 45996 | O16: Aluguel | P16: 850 | Q16: Aluguel | R16: Pix
N17: 45996 | O17: Luz | P17: 220 | Q17: Luz | R17: Pix
N18: 45996 | O18: Cartão | P18: =SUM('jan-26'!P35) -> 555.93 | Q18: Fatura | R18: Pix
N19: 45996 | O19: Faculdade | P19: 143.15 | Q19: Estudos | R19: Boleto
N20: DESPESAS FIXA CARTÃO
N21: 45662 | O21: Spotify | P21: 40.9 | Q21: Streaming | R21: Crédito
N22: 45662 | O22: Disney | P22: 66.9 | Q22: Streaming | R22: Crédito
N23: 45662 | O23: Gamepass | P23: 59.99 | Q23: Streaming | R23: Crédito
N24: 45662 | O24: Claro Casa | P24: 119.9 | Q24: Internet | R24: Crédito
N25: 45662 | O25: Claro Lucas | P25: 50.08 | Q25: Internet | R25: Crédito
N26: 45662 | O26: Claro Amor | P26: 38.36 | Q26: Internet | R26: Crédito
N27: 45662 | O27: Semova Amor (3/12) | P27: 89.9 | Q27: Saúde | R27: Crédito
N28: 45662 | O28: Wellhub Lucas | P28: 89.9 | Q28: Saúde | R28: Crédito
O35: Fatura prox. Mês | P35: =SUMIF(F6:F35, "Crédito", D6:D35) + SUMIF(L6:L35, "Crédito", J6:J35) + SUMIF(R16:R33, "Crédito", P16:P33) -> 555.93
